Workbook
Name Slicer_Statement_Type: #N/A
Name Slicer_Year: #N/A

Sheet COCA COLA CO
A1: Data provided by SimFin
A3: Profit & Loss statement
B4: in million USD | C4: FY '09 | D4: FY '10 | E4: FY '11 | F4: FY '12 | G4: FY '13 | H4: FY '14 | I4: FY '15 | J4: FY '16 | K4: FY '17 | L4: FY '18
B5: NET OPERATING REVENUES | C5: 30990 | D5: 35119 | E5: 46542 | F5: 48017 | G5: 46854 | H5: 45998 | I5: 44294 | J5: 41863 | K5: 35410 | L5: 31856
B6: Cost of goods sold | C6: 11088 | D6: 12693 | E6: 18215 | F6: 19053 | G6: 18421 | H6: 17889 | I6: 17482 | J6: 16465 | K6: 13255 | L6: 11770
B7: Gross Profit | C7: 19902 | D7: 22426 | E7: 28327 | F7: 28964 | G7: 28433 | H7: 28109 | I7: 26812 | J7: 25398 | K7: 22155 | L7: 20086
B8: Selling, general and administrative expenses | C8: 11358 | D8: 13194 | E8: 17422 | F8: 17738 | G8: 17310 | H8: 17218 | I8: 16427 | J8: 15262 | K8: 12654 | L8: 10307
B9: Other operating charges | C9: 313 | D9: 819 | E9: 732 | F9: 447 | G9: 895 | H9: 1183 | I9: 1657 | J9: 1510 | K9: 1902 | L9: 1079
B10: Operating Income | C10: 8231 | D10: 8413 | E10: 10173 | F10: 10779 | G10: 10228 | H10: 9708 | I10: 8728 | J10: 8626 | K10: 7599 | L10: 8700
B11: Interest income | C11: 249 | D11: 317 | E11: 483 | F11: 471 | G11: 534 | H11: 594 | I11: 613 | J11: 642 | K11: 677 | L11: 682
B12: Interest expense | C12: 355 | D12: 733 | E12: 417 | F12: 397 | G12: 463 | H12: 483 | I12: 856 | J12: 733 | K12: 841 | L12: 919
B13: Equity income (loss) - net | C13: 781 | D13: 1025 | E13: 690 | F13: 819 | G13: 602 | H13: 769 | I13: 489 | J13: 835 | K13: 1071 | L13: 1008
B14: Other income (loss) - net | C14: 40 | D14: 5185 | E14: 529 | F14: 137 | G14: 576 | H14: -1263 | I14: 631 | J14: -1234 | K14: -1764 | L14: -1121
B15: Income before income taxes | C15: 8946 | D15: 14207 | E15: 11458 | F15: 11809 | G15: 11477 | H15: 9325 | I15: 9605 | J15: 8136 | K15: 6742 | L15: 8350
B16: Income taxes | C16: 2040 | D16: 2370 | E16: 2812 | F16: 2723 | G16: 2851 | H16: 2201 | I16: 2239 | J16: 1586 | K16: 5560 | L16: 1623
... B18: Less: Net income attributable to noncontrolling interests | C18: 82 | D18: 50 | E18: 62 | F18: 67 | G18: 42 | H18: 26 | I18: 15 | J18: 23 | K18: 35 | L18: 42
B19: Net income from continuing operations | I19: 7366 | J19: 6550 | K19: 1182 | L19: 6727
B20: Income (Loss) from Discontinued Operations, Net of Tax, Including Portion Attributable to Noncontrolling Interest | I20: 0 | J20: 0 | K20: 101 | L20: -251
B21: NET INCOME ATTRIBUTABLE TO SHAREOWNERS OF THE COCA-COLA COMPANY | C21: 6824 | D21: 11787 | E21: 8584 | F21: 9019 | G21: 8584 | H21: 7098 | I21: 7351 | J21: 6527 | K21: 1248 | L21: 6434
A23: Balance Sheet
B24: in million USD | C24: FY '09 | D24: FY '10 | E24: FY '11 | F24: FY '12 | G24: FY '13 | H24: FY '14 | I24: FY '15 | J24: FY '16 | K24: FY '17 | L24: FY '18
B25: Assets
B26: Cash and cash equivalents | C26: 7021 | D26: 8517 | E26: 12803 | F26: 8442 | G26: 10414 | H26: 8958 | I26: 7309 | J26: 8555 | K26: 6006 | L26: 8926
B27: Short-term investments | C27: 2130 | D27: 2682 | E27: 1088 | F27: 5017 | G27: 6707 | H27: 9052 | I27: 8322 | J27: 9595 | K27: 9352 | L27: 2025
B28: Total cash, cash equivalents and short-term investments | C28: 9151 | D28: 11199 | E28: 13891 | F28: 13459 | G28: 17121 | H28: 18010 | I28: 15631 | J28: 18150 | K28: 15358 | L28: 10951
B29: Marketable securities | C29: 62 | D29: 138 | E29: 144 | F29: 3092 | G29: 3147 | H29: 3665 | I29: 4269 | J29: 4051 | K29: 5317 | L29: 5013
B30: Trade accounts receivable, less allowances | C30: 3758 | D30: 4430 | E30: 4920 | F30: 4759 | G30: 4873 | H30: 4466 | I30: 3941 | J30: 3856 | K30: 3667 | L30: 3396
B31: Inventories | C31: 2354 | D31: 2650 | E31: 3092 | F31: 3264 | G31: 3277 | H31: 3100 | I31: 2902 | J31: 2675 | K31: 2655 | L31: 2766
B32: Prepaid expenses and other assets | C32: 2226 | D32: 3162 | E32: 3450 | F32: 2781 | G32: 2886 | H32: 3066 | I32: 2752 | J32: 2481 | K32: 2000 | L32: 1962
B33: Assets held for sale | E33: 0 | F33: 2973 | G33: 0 | H33: 679 | I33: 3900 | J33: 0 | K33: 7329 | L33: 6546
B34: Assets held for sale | J34: 2797 | K34: 219 | L34: 0
B35: Total current assets | C35: 17551 | D35: 21579 | E35: 25497 | F35: 30328 | G35: 31304 | H35: 32986 | I35: 33395 | J35: 34010 | K35: 36545 | L35: 30634
B36: Equity method investments | C36: 6217 | D36: 6954 | E36: 7233 | F36: 9216 | G36: 10393 | H36: 9947 | I36: 12318 | J36: 16260 | K36: 20856 | L36: 19407
B37: Other investments | C37: 538 | D37: 631 | E37: 1141 | F37: 1232 | G37: 1119 | H37: 3678 | I37: 3470 | J37: 989 | K37: 1096 | L37: 867
B38: Other assets | C38: 1976 | D38: 2121 | E38: 3495 | F38: 3585 | G38: 4661 | H38: 4407 | I38: 4110 | J38: 4248 | K38: 4230 | L38: 4139
B39: Property, plant and equipment - net | C39: 9561 | D39: 14727 | E39: 14939 | F39: 14476 | G39: 14967 | H39: 14633 | I39: 12571 | J39: 10635 | K39: 8203 | L39: 8232
B40: Deferred income tax assets | K40: 330 | L40: 2667
B41: TRADEMARKS WITH INDEFINITE LIVES | C41: 6183 | D41: 6356 | E41: 6430 | F41: 6527 | G41: 6744 | H41: 6533 | I41: 5989 | J41: 6097 | K41: 6729 | L41: 6682
B42: BOTTLERS' FRANCHISE RIGHTS WITH INDEFINITE LIVES | C42: 1953 | D42: 7511 | E42: 7770 | F42: 7405 | G42: 7415 | H42: 6689 | I42: 6000 | J42: 3676 | K42: 138 | L42: 51
B43: Goodwill | C43: 4224 | D43: 11665 | E43: 12219 | F43: 12255 | G43: 12312 | H43: 12100 | I43: 11289 | J43: 10629 | K43: 9401 | L43: 10263
B44: Other intangible assets | C44: 468 | D44: 1377 | E44: 1250 | F44: 1150 | G44: 1140 | H44: 1050 | I44: 854 | J44: 726 | K44: 368 | L44: 274
B45: Total assets | C45: 48671 | D45: 72921 | E45: 79974 | F45: 86174 | G45: 90055 | H45: 92023 | I45: 89996 | J45: 87270 | K45: 87896 | L45: 83216
B46: Liabilities
B47: Accounts payable and accrued expenses | C47: 6657 | D47: 8859 | E47: 9009 | F47: 8680 | G47: 9577 | H47: 9234 | I47: 9660 | J47: 9490 | K47: 8748 | L47: 8932
B48: Loans and notes payable | C48: 6749 | D48: 8100 | E48: 12871 | F48: 16297 | G48: 16901 | H48: 19130 | I48: 13129 | J48: 12498 | K48: 13205 | L48: 13194
B49: Current maturities of long-term debt | C49: 51 | D49: 1276 | E49: 2041 | F49: 1577 | G49: 1024 | H49: 3552 | I49: 2676 | J49: 3527 | K49: 3298 | L49: 4997
B50: Accrued income taxes | C50: 264 | D50: 273 | E50: 362 | F50: 471 | G50: 309 | H50: 400 | I50: 331 | J50: 307 | K50: 410 | L50: 378
B51: Liabilities held for sale | E51: 0 | F51: 796 | G51: 0 | H51: 58 | I51: 1133 | J51: 710 | K51: 37 | L51: 0
B52: Liabilities Held for Sale, Discontinued Operations | J52: 0 | K52: 1496 | L52: 1722
B53: Total current liabilities | C53: 13721 | D53: 18508 | E53: 24283 | F53: 27821 | G53: 27811 | H53: 32374 | I53: 26929 | J53: 26532 | K53: 27194 | L53: 29223
B54: Long-term debt | C54: 5059 | D54: 14041 | E54: 13656 | F54: 14736 | G54: 19154 | H54: 19063 | I54: 28311 | J54: 29684 | K54: 31182 | L54: 25364
B55: Other liabilities | C55: 2965 | D55: 4794 | E55: 5420 | F55: 5468 | G55: 3498 | H55: 4389 | I55: 4301 | J55: 4081 | K55: 8021 | L55: 7638
B56: Deferred income taxes | C56: 1580 | D56: 4261 | E56: 4694 | F56: 4981 | G56: 6152 | H56: 5636 | I56: 4691 | J56: 3753 | K56: 2522 | L56: 1933
B57: Common stock | C57: 880 | D57: 880 | E57: 1760 | F57: 1760 | G57: 1760 | H57: 1760 | I57: 1760 | J57: 1760 | K57: 1760 | L57: 1760
B58: Capital surplus | C58: 8537 | D58: 10057 | E58: 10332 | F58: 11379 | G58: 12276 | H58: 13154 | I58: 14016 | J58: 14993 | K58: 15864 | L58: 16520
B59: Reinvested earnings | C59: 41537 | D59: 49278 | E59: 53621 | F59: 58045 | G59: 61660 | H59: 63408 | I59: 65018 | J59: 65502 | K59: 60430 | L59: 63234
B60: Accumulated other comprehensive income (loss) | C60: -757 | D60: -1450 | E60: -2774 | F60: -3385 | G60: -3432 | H60: -5777 | I60: -10174 | J60: -11205 | K60: -10305 | L60: -12814
B61: Treasury stock, at cost | C61: -25398 | D61: -27762 | E61: -31304 | F61: -35009 | G61: -39091 | H61: -42225 | I61: -45066 | J61: -47988 | K61: -50677 | L61: -51719
B62: EQUITY ATTRIBUTABLE TO SHAREOWNERS OF THE COCA-COLA COMPANY | C62: 24799 | D62: 31003 | E62: 31635 | F62: 32790 | G62: 33173 | H62: 30320 | I62: 25554 | J62: 23062 | K62: 17072 | L62: 16981
B63: Equity attributable to noncontrolling interests | C63: 547 | D63: 314 | E63: 286 | F63: 378 | G63: 267 | H63: 241 | I63: 210 | J63: 158 | K63: 1905 | L63: 2077
B64: Total equity | C64: 25346 | D64: 31317 | E64: 31921 | F64: 33168 | G64: 33440 | H64: 30561 | I64: 25764 | J64: 23220 | K64: 18977 | L64: 19058
B65: Total liabilities and equity | C65: 48671 | D65: 72921 | E65: 79974 | F65: 86174 | G65: 90055 | H65: 92023 | I65: 89996 | J65: 87270 | K65: 87896 | L65: 83216
A67: Cash Flow statement
B68: in million USD | C68: FY '09 | D68: FY '10 | E68: FY '11 | F68: FY '12 | G68: FY '13 | H68: FY '14 | I68: FY '15 | J68: FY '16 | K68: FY '17 | L68: FY '18
B69: CONSOLIDATED NET INCOME | C69: 6906 | D69: 11837 | E69: 8646 | F69: 9086 | G69: 8626 | H69: 7124 | I69: 7366 | J69: 6550 | K69: 1283 | L69: 6476
B70: Depreciation and amortization | C70: 1236 | D70: 1443 | E70: 1954 | F70: 1982 | G70: 1977 | H70: 1976 | I70: 1970 | J70: 1787 | K70: 1260 | L70: 1086
B71: (Income) Loss from discontinued operations | I71: 0 | J71: 0 | K71: -101 | L71: 251
B72: Net income from continuing operations | I72: 7366 | J72: 6550 | K72: 1182 | L72: 6727
B73: Stock-based compensation expense | C73: 241 | D73: 380 | E73: 354 | F73: 259 | G73: 227 | H73: 209 | I73: 236 | J73: 258 | K73: 219 | L73: 225
B74: Deferred income taxes | C74: 353 | D74: 604 | E74: 1035 | F74: 632 | G74: 648 | H74: -40 | I74: 73 | J74: -856 | K74: -1256 | L74: -450
B75: Equity (income) loss - net of dividends | C75: -359 | D75: -671 | E75: -269 | F75: -426 | G75: -201 | H75: -371 | I75: -122 | J75: -449 | K75: -628 | L75: -457
B76: Foreign currency adjustments | C76: 61 | D76: 151 | E76: 7 | F76: -130 | G76: 168 | H76: 415 | I76: -137 | J76: 158 | K76: 281 | L76: -38
B77: Significant (gains) losses on sales of assets - net | C77: -43 | D77: -645 | E77: -220 | F77: -98 | G77: -670 | H77: 831 | I77: -374 | J77: 1146 | K77: 1459 | L77: 189
B78: Other significant (gains) losses - net | C78: 0 | D78: -4713
B79: Other operating charges | C79: 134 | D79: 264 | E79: 214 | F79: 166 | G79: 465 | H79: 761 | I79: 929 | J79: 647 | K79: 1218 | L79: 558
B80: Other items | C80: 221 | D80: 512 | E80: -354 | F80: 254 | G80: 234 | H80: 149 | I80: 744 | J80: -224 | K80: -269 | L80: 682
B81: Net change in operating assets and liabilities | C81: -564 | D81: 370 | E81: -1893 | F81: -1080 | G81: -932 | H81: -439 | I81: -157 | J81: -221 | K81: 3464 | L81: -1202
B82: Net cash provided by operating activities | C82: 8186 | D82: 9532 | E82: 9474 | F82: 10645 | G82: 10542 | H82: 10615 | I82: 10528 | J82: 8796 | K82: 6930 | L82: 7320
B83: Purchases of short-term investments | C83: -2130 | D83: -4579
B84: Purchases of investments | C84: -22 | D84: -132 | E84: -4798 | F84: -14824 | G84: -14782 | H84: -17800 | I84: -15831 | J84: -15499 | K84: -17296 | L84: -7789
B85: Proceeds from disposals of investments | C85: 0 | D85: 4032 | E85: 5811 | F85: 7791 | G85: 12791 | H85: 12986 | I85: 14079 | J85: 16624 | K85: 16694 | L85: 14977
B86: Acquisitions of businesses, equity method investments and nonmarketable securities | C86: -300 | D86: -2511 | E86: -971 | F86: -1486 | G86: -353 | H86: -389 | I86: -2491 | J86: -838 | K86: -3809 | L86: -1040
B87: Proceeds from disposals of businesses, equity method investments and nonmarkatable securities | C87: 240 | D87: 972 | E87: 398 | F87: 20 | G87: 872 | H87: 148 | I87: 565 | J87: 1035 | K87: 3821 | L87: 1362
B88: Purchases of property, plant and equipment | C88: -1993 | D88: -2215 | E88: -2920 | F88: -2780 | G88: -2550 | H88: -2406 | I88: -2553 | J88: -2262 | K88: -1675 | L88: -1347
B89: Proceeds from disposals of property, plant and equipment | C89: 104 | D89: 134 | E89: 101 | F89: 143 | G89: 111 | H89: 223 | I89: 85 | J89: 150 | K89: 104 | L89: 245
B90: Other investing activities | C90: -48 | D90: -106 | E90: -145 | F90: -268 | G90: -303 | H90: -268 | I90: -40 | J90: -209 | K90: -93 | L90: -60
B91: Net cash provided by (used in) investing activities | C91: -4149 | D91: -4405 | E91: -2524 | F91: -11404 | G91: -4214 | H91: -7506 | I91: -6186 | J91: -999 | K91: -2254 | L91: 6348
B92: Issuances of debt | C92: 14689 | D92: 15251 | E92: 27495 | F92: 42791 | G92: 43425 | H92: 41674 | I92: 40434 | J92: 27281 | K92: 29857 | L92: 27339
B93: Payments of debt | C93: -12326 | D93: -13403 | E93: -22530 | F93: -38573 | G93: -38714 | H93: -36962 | I93: -37738 | J93: -25615 | K93: -28768 | L93: -30568
B94: Issuances of stock | C94: 664 | D94: 1666 | E94: 1569 | F94: 1489 | G94: 1328 | H94: 1532 | I94: 1245 | J94: 1434 | K94: 1595 | L94: 1476
B95: Purchases of stock for treasury | C95: -1518 | D95: -2961 | E95: -4513 | F95: -4559 | G95: -4832 | H95: -4162 | I95: -3564 | J95: -3681 | K95: -3682 | L95: -1912
... B98: Net cash provided by (used in) financing activities | C98: -2293 | D98: -3465 | E98: -2234 | F98: -3347 | G98: -3745 | H98: -3631 | I98: -5113 | J98: -6545 | K98: -7409 | L98: -10552
B99: Cash Provided by (Used in) Operating Activities, Discontinued Operations | I99: 0 | J99: 0 | K99: 111 | L99: 307
B100: Effect of exchange rate changes on cash and cash equivalents | C100: 576 | D100: -166 | E100: -430 | F100: -255 | G100: -611 | H100: -934 | I100: -878 | J100: -6 | K100: 241 | L100: -262
B101: Cash Provided by (Used in) Investing Activities, Discontinued Operations | I101: 0 | J101: 0 | K101: -58 | L101: -421
B102: Cash Provided by (Used in) Financing Activities, Discontinued Operations | I102: 0 | J102: 0 | K102: -38 | L102: 205
B103: Net Cash Provided by (Used in) Discontinued Operations | I103: 0 | J103: 0 | K103: 15 | L103: 91
B104: Net increase (decrease) during the year | C104: 2320 | D104: 1496 | E104: 4286 | F104: -4361 | G104: 1972 | H104: -1456 | I104: -1649 | J104: 1246 | K104: -2477 | L104: 2945

Sheet Pivot Table 1(Viewing Only)
A3: Row Labels | B3: Sum of Amount
A4: 2009 | B4: 399741
A5: Balance Sheet | B5: 285252
A6: Accounts payable and accrued expenses | B6: 6657
A7: Accrued income taxes | B7: 264
A8: Accumulated other comprehensive income (loss) | B8: -757
A9: Assets held for sale | B9: 0
A10: BOTTLERS' FRANCHISE RIGHTS WITH INDEFINITE LIVES | B10: 1953
A11: Capital surplus | B11: 8537
A12: Cash and cash equivalents | B12: 7021
A13: Common stock | B13: 880
A14: Current maturities of long-term debt | B14: 51
A15: Deferred income tax assets | B15: 0
A16: Deferred income taxes | B16: 1580
... A99: Selling, general and administrative expenses | B99: 11358
A100: 2010 | B100: 550119
A101: Balance Sheet | B101: 405290
A102: Accounts payable and accrued expenses | B102: 8859
A103: Accrued income taxes | B103: 273
A104: Accumulated other comprehensive income (loss) | B104: -1450
A105: Assets held for sale | B105: 0
A106: BOTTLERS' FRANCHISE RIGHTS WITH INDEFINITE LIVES | B106: 7511
A107: Capital surplus | B107: 10057
A108: Cash and cash equivalents | B108: 8517
A109: Common stock | B109: 880
A110: Current maturities of long-term debt | B110: 1276
A111: Deferred income tax assets | B111: 0
A112: Deferred income taxes | B112: 4261
... A195: Selling, general and administrative expenses | B195: 13194
A196: 2011 | B196: 615503
A197: Balance Sheet | B197: 447123
A198: Accounts payable and accrued expenses | B198: 9009
A199: Accrued income taxes | B199: 362
A200: Accumulated other comprehensive income (loss) | B200: -2774
A201: Assets held for sale | B201: 0
A202: BOTTLERS' FRANCHISE RIGHTS WITH INDEFINITE LIVES | B202: 7770
A203: Capital surplus | B203: 10332
A204: Cash and cash equivalents | B204: 12803
A205: Common stock | B205: 1760
A206: Current maturities of long-term debt | B206: 2041
A207: Deferred income tax assets | B207: 0
A208: Deferred income taxes | B208: 4694
... A291: Selling, general and administrative expenses | B291: 17422
A292: 2012 | B292: 628960
A293: Balance Sheet | B293: 482262
A294: Accounts payable and accrued expenses | B294: 8680
A295: Accrued income taxes | B295: 471
A296: Accumulated other comprehensive income (loss) | B296: -3385
A297: Assets held for sale | B297: 2973
A298: BOTTLERS' FRANCHISE RIGHTS WITH INDEFINITE LIVES | B298: 7405
A299: Capital surplus | B299: 11379
A300: Cash and cash equivalents | B300: 8442
A301: Common stock | B301: 1760
A302: Current maturities of long-term debt | B302: 1577
A303: Deferred income tax assets | B303: 0
A304: Deferred income taxes | B304: 4981
... A387: Selling, general and administrative expenses | B387: 17738
A388: 2013 | B388: 665492
A389: Balance Sheet | B389: 503069
A390: Accounts payable and accrued expenses | B390: 9577
A391: Accrued income taxes | B391: 309
A392: Accumulated other comprehensive income (loss) | B392: -3432
A393: Assets held for sale | B393: 0
A394: BOTTLERS' FRANCHISE RIGHTS WITH INDEFINITE LIVES | B394: 7415
A395: Capital surplus | B395: 12276
A396: Cash and cash equivalents | B396: 10414
A397: Common stock | B397: 1760
A398: Current maturities of long-term debt | B398: 1024
A399: Deferred income tax assets | B399: 0
A400: Deferred income taxes | B400: 6152
... A483: Selling, general and administrative expenses | B483: 17310
A484: 2014 | B484: 655371
A485: Balance Sheet | B485: 512343
A486: Accounts payable and accrued expenses | B486: 9234
A487: Accrued income taxes | B487: 400
A488: Accumulated other comprehensive income (loss) | B488: -5777
A489: Assets held for sale | B489: 679
A490: BOTTLERS' FRANCHISE RIGHTS WITH INDEFINITE LIVES | B490: 6689
A491: Capital surplus | B491: 13154
A492: Cash and cash equivalents | B492: 8958
A493: Common stock | B493: 1760
A494: Current maturities of long-term debt | B494: 3552
A495: Deferred income tax assets | B495: 0
A496: Deferred income taxes | B496: 5636
... A579: Selling, general and administrative expenses | B579: 17218
A580: 2015 | B580: 642485
A581: Balance Sheet | B581: 487257
A582: Accounts payable and accrued expenses | B582: 9660
A583: Accrued income taxes | B583: 331
A584: Accumulated other comprehensive income (loss) | B584: -10174
A585: Assets held for sale | B585: 3900
A586: BOTTLERS' FRANCHISE RIGHTS WITH INDEFINITE LIVES | B586: 6000
A587: Capital surplus | B587: 14016
A588: Cash and cash equivalents | B588: 7309
A589: Common stock | B589: 1760
A590: Current maturities of long-term debt | B590: 2676
A591: Deferred income tax assets | B591: 0
A592: Deferred income taxes | B592: 4691
... A675: Selling, general and administrative expenses | B675: 16427
A676: 2016 | B676: 623820
...

Sheet Table Format
A1: Statement_type | B1: Metric | C1: Year | D1: Amount | H1: Xlookup
A2: Profit & Loss Statement | B2: NET OPERATING REVENUES | C2: 2009 | D2: ='COCA COLA CO'!C5 -> 30990 | H2: Profit & Loss Statement | I2: NET INCOME ATTRIBUTABLE TO SHAREOWNERS OF THE COCA-COLA COMPANY
A3: Profit & Loss Statement | B3: Cost of goods sold | C3: 2009 | D3: ='COCA COLA CO'!C6 -> 11088 | H3: Balance Sheet | I3: Total Assets
A4: Profit & Loss Statement | B4: Gross Profit | C4: 2009 | D4: ='COCA COLA CO'!C7 -> 19902 | H4: Cash Flow Statement | I4: Net increase (decrease) during the year
A5: Profit & Loss Statement | B5: Selling, general and administrative expenses | C5: 2009 | D5: ='COCA COLA CO'!C8 -> 11358
A6: Profit & Loss Statement | B6: Other operating charges | C6: 2009 | D6: ='COCA COLA CO'!C9 -> 313
A7: Profit & Loss Statement | B7: Operating Income | C7: 2009 | D7: ='COCA COLA CO'!C10 -> 8231
A8: Profit & Loss Statement | B8: Interest income | C8: 2009 | D8: ='COCA COLA CO'!C11 -> 249
A9: Profit & Loss Statement | B9: Interest expense | C9: 2009 | D9: ='COCA COLA CO'!C12 -> 355
A10: Profit & Loss Statement | B10: Equity income (loss) - net | C10: 2009 | D10: ='COCA COLA CO'!C13 -> 781
A11: Profit & Loss Statement | B11: Other income (loss) - net | C11: 2009 | D11: ='COCA COLA CO'!C14 -> 40
A12: Profit & Loss Statement | B12: Income before income taxes | C12: 2009 | D12: ='COCA COLA CO'!C15 -> 8946
A13: Profit & Loss Statement | B13: Income taxes | C13: 2009 | D13: ='COCA COLA CO'!C16 -> 2040
A14: Profit & Loss Statement | B14: CONSOLIDATED NET INCOME | C14: 2009 | D14: ='COCA COLA CO'!C17 -> 6906
A15: Profit & Loss Statement | B15: Less: Net income attributable to noncontrolling interests | C15: 2009 | D15: ='COCA COLA CO'!C18 -> 82
A16: Profit & Loss Statement | B16: Net income from continuing operations | C16: 2009 | D16: ='COCA COLA CO'!C19 -> 0
... A18: Profit & Loss Statement | B18: NET INCOME ATTRIBUTABLE TO SHAREOWNERS OF THE COCA-COLA COMPANY | C18: 2009 | D18: ='COCA COLA CO'!C21 -> 6824
A19: Profit & Loss Statement | B19: NET OPERATING REVENUES | C19: 2010 | D19: ='COCA COLA CO'!D5 -> 35119
A20: Profit & Loss Statement | B20: Cost of goods sold | C20: 2010 | D20: ='COCA COLA CO'!D6 -> 12693
A21: Profit & Loss Statement | B21: Gross Profit | C21: 2010 | D21: ='COCA COLA CO'!D7 -> 22426
A22: Profit & Loss Statement | B22: Selling, general and administrative expenses | C22: 2010 | D22: ='COCA COLA CO'!D8 -> 13194
A23: Profit & Loss Statement | B23: Other operating charges | C23: 2010 | D23: ='COCA COLA CO'!D9 -> 819
A24: Profit & Loss Statement | B24: Operating Income | C24: 2010 | D24: ='COCA COLA CO'!D10 -> 8413
A25: Profit & Loss Statement | B25: Interest income | C25: 2010 | D25: ='COCA COLA CO'!D11 -> 317
A26: Profit & Loss Statement | B26: Interest expense | C26: 2010 | D26: ='COCA COLA CO'!D12 -> 733
A27: Profit & Loss Statement | B27: Equity income (loss) - net | C27: 2010 | D27: ='COCA COLA CO'!D13 -> 1025
A28: Profit & Loss Statement | B28: Other income (loss) - net | C28: 2010 | D28: ='COCA COLA CO'!D14 -> 5185
A29: Profit & Loss Statement | B29: Income before income taxes | C29: 2010 | D29: ='COCA COLA CO'!D15 -> 14207
A30: Profit & Loss Statement | B30: Income taxes | C30: 2010 | D30: ='COCA COLA CO'!D16 -> 2370
... A35: Profit & Loss Statement | B35: NET INCOME ATTRIBUTABLE TO SHAREOWNERS OF THE COCA-COLA COMPANY | C35: 2010 | D35: ='COCA COLA CO'!D21 -> 11787
A36: Profit & Loss Statement | B36: NET OPERATING REVENUES | C36: 2011 | D36: ='COCA COLA CO'!E5 -> 46542
A37: Profit & Loss Statement | B37: Cost of goods sold | C37: 2011 | D37: ='COCA COLA CO'!E6 -> 18215
A38: Profit & Loss Statement | B38: Gross Profit | C38: 2011 | D38: ='COCA COLA CO'!E7 -> 28327
A39: Profit & Loss Statement | B39: Selling, general and administrative expenses | C39: 2011 | D39: ='COCA COLA CO'!E8 -> 17422
A40: Profit & Loss Statement | B40: Other operating charges | C40: 2011 | D40: ='COCA COLA CO'!E9 -> 732
A41: Profit & Loss Statement | B41: Operating Income | C41: 2011 | D41: ='COCA COLA CO'!E10 -> 10173
A42: Profit & Loss Statement | B42: Interest income | C42: 2011 | D42: ='COCA COLA CO'!E11 -> 483
A43: Profit & Loss Statement | B43: Interest expense | C43: 2011 | D43: ='COCA COLA CO'!E12 -> 417
A44: Profit & Loss Statement | B44: Equity income (loss) - net | C44: 2011 | D44: ='COCA COLA CO'!E13 -> 690
A45: Profit & Loss Statement | B45: Other income (loss) - net | C45: 2011 | D45: ='COCA COLA CO'!E14 -> 529
A46: Profit & Loss Statement | B46: Income before income taxes | C46: 2011 | D46: ='COCA COLA CO'!E15 -> 11458
A47: Profit & Loss Statement | B47: Income taxes | C47: 2011 | D47: ='COCA COLA CO'!E16 -> 2812
... A52: Profit & Loss Statement | B52: NET INCOME ATTRIBUTABLE TO SHAREOWNERS OF THE COCA-COLA COMPANY | C52: 2011 | D52: ='COCA COLA CO'!E21 -> 8584
A53: Profit & Loss Statement | B53: NET OPERATING REVENUES | C53: 2012 | D53: ='COCA COLA CO'!F5 -> 48017
A54: Profit & Loss Statement | B54: Cost of goods sold | C54: 2012 | D54: ='COCA COLA CO'!F6 -> 19053
A55: Profit & Loss Statement | B55: Gross Profit | C55: 2012 | D55: ='COCA COLA CO'!F7 -> 28964
A56: Profit & Loss Statement | B56: Selling, general and administrative expenses | C56: 2012 | D56: ='COCA COLA CO'!F8 -> 17738
A57: Profit & Loss Statement | B57: Other operating charges | C57: 2012 | D57: ='COCA COLA CO'!F9 -> 447
A58: Profit & Loss Statement | B58: Operating Income | C58: 2012 | D58: ='COCA COLA CO'!F10 -> 10779
A59: Profit & Loss Statement | B59: Interest income | C59: 2012 | D59: ='COCA COLA CO'!F11 -> 471
A60: Profit & Loss Statement | B60: Interest expense | C60: 2012 | D60: ='COCA COLA CO'!F12 -> 397
A61: Profit & Loss Statement | B61: Equity income (loss) - net | C61: 2012 | D61: ='COCA COLA CO'!F13 -> 819
A62: Profit & Loss Statement | B62: Other income (loss) - net | C62: 2012 | D62: ='COCA COLA CO'!F14 -> 137
A63: Profit & Loss Statement | B63: Income before income taxes | C63: 2012 | D63: ='COCA COLA CO'!F15 -> 11809
A64: Profit & Loss Statement | B64: Income taxes | C64: 2012 | D64: ='COCA COLA CO'!F16 -> 2723
... A69: Profit & Loss Statement | B69: NET INCOME ATTRIBUTABLE TO SHAREOWNERS OF THE COCA-COLA COMPANY | C69: 2012 | D69: ='COCA COLA CO'!F21 -> 9019
A70: Profit & Loss Statement | B70: NET OPERATING REVENUES | C70: 2013 | D70: ='COCA COLA CO'!G5 -> 46854
A71: Profit & Loss Statement | B71: Cost of goods sold | C71: 2013 | D71: ='COCA COLA CO'!G6 -> 18421
A72: Profit & Loss Statement | B72: Gross Profit | C72: 2013 | D72: ='COCA COLA CO'!G7 -> 28433
A73: Profit & Loss Statement | B73: Selling, general and administrative expenses | C73: 2013 | D73: ='COCA COLA CO'!G8 -> 17310
A74: Profit & Loss Statement | B74: Other operating charges | C74: 2013 | D74: ='COCA COLA CO'!G9 -> 895
A75: Profit & Loss Statement | B75: Operating Income | C75: 2013 | D75: ='COCA COLA CO'!G10 -> 10228
A76: Profit & Loss Statement | B76: Interest income | C76: 2013 | D76: ='COCA COLA CO'!G11 -> 534
A77: Profit & Loss Statement | B77: Interest expense | C77: 2013 | D77: ='COCA COLA CO'!G12 -> 463
A78: Profit & Loss Statement | B78: Equity income (loss) - net | C78: 2013 | D78: ='COCA COLA CO'!G13 -> 602
A79: Profit & Loss Statement | B79: Other income (loss) - net | C79: 2013 | D79: ='COCA COLA CO'!G14 -> 576
A80: Profit & Loss Statement | B80: Income before income taxes | C80: 2013 | D80: ='COCA COLA CO'!G15 -> 11477
A81: Profit & Loss Statement | B81: Income taxes | C81: 2013 | D81: ='COCA COLA CO'!G16 -> 2851
... A86: Profit & Loss Statement | B86: NET INCOME ATTRIBUTABLE TO SHAREOWNERS OF THE COCA-COLA COMPANY | C86: 2013 | D86: ='COCA COLA CO'!G21 -> 8584
A87: Profit & Loss Statement | B87: NET OPERATING REVENUES | C87: 2014 | D87: ='COCA COLA CO'!H5 -> 45998
A88: Profit & Loss Statement | B88: Cost of goods sold | C88: 2014 | D88: ='COCA COLA CO'!H6 -> 17889
A89: Profit & Loss Statement | B89: Gross Profit | C89: 2014 | D89: ='COCA COLA CO'!H7 -> 28109
A90: Profit & Loss Statement | B90: Selling, general and administrative expenses | C90: 2014 | D90: ='COCA COLA CO'!H8 -> 17218
A91: Profit & Loss Statement | B91: Other operating charges | C91: 2014 | D91: ='COCA COLA CO'!H9 -> 1183
A92: Profit & Loss Statement | B92: Operating Income | C92: 2014 | D92: ='COCA COLA CO'!H10 -> 9708
A93: Profit & Loss Statement | B93: Interest income | C93: 2014 | D93: ='COCA COLA CO'!H11 -> 594
A94: Profit & Loss Statement | B94: Interest expense | C94: 2014 | D94: ='COCA COLA CO'!H12 -> 483
A95: Profit & Loss Statement | B95: Equity income (loss) - net | C95: 2014 | D95: ='COCA COLA CO'!H13 -> 769
A96: Profit & Loss Statement | B96: Other income (loss) - net | C96: 2014 | D96: ='COCA COLA CO'!H14 -> -1263
A97: Profit & Loss Statement | B97: Income before income taxes | C97: 2014 | D97: ='COCA COLA CO'!H15 -> 9325
A98: Profit & Loss Statement | B98: Income taxes | C98: 2014 | D98: ='COCA COLA CO'!H16 -> 2201
... A103: Profit & Loss Statement | B103: NET INCOME ATTRIBUTABLE TO SHAREOWNERS OF THE COCA-COLA COMPANY | C103: 2014 | D103: ='COCA COLA CO'!H21 -> 7098
A104: Profit & Loss Statement | B104: NET OPERATING REVENUES | C104: 2015 | D104: ='COCA COLA CO'!I5 -> 44294
A105: Profit & Loss Statement | B105: Cost of goods sold | C105: 2015 | D105: ='COCA COLA CO'!I6 -> 17482
A106: Profit & Loss Statement | B106: Gross Profit | C106: 2015 | D106: ='COCA COLA CO'!I7 -> 26812
A107: Profit & Loss Statement | B107: Selling, general and administrative expenses | C107: 2015 | D107: ='COCA COLA CO'!I8 -> 16427
A108: Profit & Loss Statement | B108: Other operating charges | C108: 2015 | D108: ='COCA COLA CO'!I9 -> 1657
A109: Profit & Loss Statement | B109: Operating Income | C109: 2015 | D109: ='COCA COLA CO'!I10 -> 8728
A110: Profit & Loss Statement | B110: Interest income | C110: 2015 | D110: ='COCA COLA CO'!I11 -> 613
A111: Profit & Loss Statement | B111: Interest expense | C111: 2015 | D111: ='COCA COLA CO'!I12 -> 856
A112: Profit & Loss Statement | B112: Equity income (loss) - net | C112: 2015 | D112: ='COCA COLA CO'!I13 -> 489
A113: Profit & Loss Statement | B113: Other income (loss) - net | C113: 2015 | D113: ='COCA COLA CO'!I14 -> 631
A114: Profit & Loss Statement | B114: Income before income taxes | C114: 2015 | D114: ='COCA COLA CO'!I15 -> 9605
A115: Profit & Loss Statement | B115: Income taxes | C115: 2015 | D115: ='COCA COLA CO'!I16 -> 2239
... A120: Profit & Loss Statement | B120: NET INCOME ATTRIBUTABLE TO SHAREOWNERS OF THE COCA-COLA COMPANY | C120: 2015 | D120: ='COCA COLA CO'!I21 -> 7351
A121: Profit & Loss Statement | B121: NET OPERATING REVENUES | C121: 2016 | D121: ='COCA COLA CO'!J5 -> 41863
A122: Profit & Loss Statement | B122: Cost of goods sold | C122: 2016 | D122: ='COCA COLA CO'!J6 -> 16465
A123: Profit & Loss Statement | B123: Gross Profit | C123: 2016 | D123: ='COCA COLA CO'!J7 -> 25398
A124: Profit & Loss Statement | B124: Selling, general and administrative expenses | C124: 2016 | D124: ='COCA COLA CO'!J8 -> 15262
A125: Profit & Loss Statement | B125: Other operating charges | C125: 2016 | D125: ='COCA COLA CO'!J9 -> 1510
...

Sheet Overall_Data
A3: Row Labels | B3: Sum of Price_Amount
A4: 2009 | B4: 57815
A5: Balance Sheet | B5: 48671
A6: Cash Flow Statement | B6: 2320
A7: Profit & Loss Statement | B7: 6824
A8: 2010 | B8: 86204
A9: Balance Sheet | B9: 72921
A10: Cash Flow Statement | B10: 1496
A11: Profit & Loss Statement | B11: 11787
A12: 2011 | B12: 92844
A13: Balance Sheet | B13: 79974
A14: Cash Flow Statement | B14: 4286
A15: Profit & Loss Statement | B15: 8584
A16: 2012 | B16: 90832
A17: Balance Sheet | B17: 86174
A18: Cash Flow Statement | B18: -4361
A19: Profit & Loss Statement | B19: 9019
A20: 2013 | B20: 100611
A21: Balance Sheet | B21: 90055
A22: Cash Flow Statement | B22: 1972
A23: Profit & Loss Statement | B23: 8584
A24: 2014 | B24: 97665
A25: Balance Sheet | B25: 92023
A26: Cash Flow Statement | B26: -1456
A27: Profit & Loss Statement | B27: 7098
A28: 2015 | B28: 95698
A29: Balance Sheet | B29: 89996
A30: Cash Flow Statement | B30: -1649
A31: Profit & Loss Statement | B31: 7351
A32: 2016 | B32: 95043
A33: Balance Sheet | B33: 87270
A34: Cash Flow Statement | B34: 1246
A35: Profit & Loss Statement | B35: 6527
A36: 2017 | B36: 86667
A37: Balance Sheet | B37: 87896
A38: Cash Flow Statement | B38: -2477
A39: Profit & Loss Statement | B39: 1248
A40: 2018 | B40: 92595
A41: Balance Sheet | B41: 83216
A42: Cash Flow Statement | B42: 2945
A43: Profit & Loss Statement | B43: 6434
A44: Grand Total | B44: 895974

Sheet Negative_Cash_Flow
A3: Row Labels | B3: Sum of Price_Amount
A4: 2012 | B4: -4361
A5: Cash Flow Statement | B5: -4361
A6: 2014 | B6: -1456
A7: Cash Flow Statement | B7: -1456
A8: 2015 | B8: -1649
A9: Cash Flow Statement | B9: -1649
A10: 2017 | B10: -2477
A11: Cash Flow Statement | B11: -2477
A12: Grand Total | B12: -9943

Sheet Main_Table
A1: Statement_Type | B1: Metric | C1: Year | D1: Price_Amount
A2: Profit & Loss Statement | B2: NET INCOME ATTRIBUTABLE TO SHAREOWNERS OF THE COCA-COLA COMPANY | C2: 2009 | D2: {=_xlfn.XLOOKUP(B2 &C2,Table3[Metric] &Table3[Year],Table3[Amount],,0)} -> 6824
A3: Profit & Loss Statement | B3: NET INCOME ATTRIBUTABLE TO SHAREOWNERS OF THE COCA-COLA COMPANY | C3: 2010 | D3: {=_xlfn.XLOOKUP(B3 &C3,Table3[Metric] &Table3[Year],Table3[Amount],,0)} -> 11787
A4: Profit & Loss Statement | B4: NET INCOME ATTRIBUTABLE TO SHAREOWNERS OF THE COCA-COLA COMPANY | C4: 2011 | D4: {=_xlfn.XLOOKUP(B4 &C4,Table3[Metric] &Table3[Year],Table3[Amount],,0)} -> 8584
A5: Profit & Loss Statement | B5: NET INCOME ATTRIBUTABLE TO SHAREOWNERS OF THE COCA-COLA COMPANY | C5: 2012 | D5: {=_xlfn.XLOOKUP(B5 &C5,Table3[Metric] &Table3[Year],Table3[Amount],,0)} -> 9019
A6: Profit & Loss Statement | B6: NET INCOME ATTRIBUTABLE TO SHAREOWNERS OF THE COCA-COLA COMPANY | C6: 2013 | D6: {=_xlfn.XLOOKUP(B6 &C6,Table3[Metric] &Table3[Year],Table3[Amount],,0)} -> 8584
A7: Profit & Loss Statement | B7: NET INCOME ATTRIBUTABLE TO SHAREOWNERS OF THE COCA-COLA COMPANY | C7: 2014 | D7: {=_xlfn.XLOOKUP(B7 &C7,Table3[Metric] &Table3[Year],Table3[Amount],,0)} -> 7098
A8: Profit & Loss Statement | B8: NET INCOME ATTRIBUTABLE TO SHAREOWNERS OF THE COCA-COLA COMPANY | C8: 2015 | D8: {=_xlfn.XLOOKUP(B8 &C8,Table3[Metric] &Table3[Year],Table3[Amount],,0)} -> 7351
A9: Profit & Loss Statement | B9: NET INCOME ATTRIBUTABLE TO SHAREOWNERS OF THE COCA-COLA COMPANY | C9: 2016 | D9: {=_xlfn.XLOOKUP(B9 &C9,Table3[Metric] &Table3[Year],Table3[Amount],,0)} -> 6527
A10: Profit & Loss Statement | B10: NET INCOME ATTRIBUTABLE TO SHAREOWNERS OF THE COCA-COLA COMPANY | C10: 2017 | D10: {=_xlfn.XLOOKUP(B10 &C10,Table3[Metric] &Table3[Year],Table3[Amount],,0)} -> 1248
A11: Profit & Loss Statement | B11: NET INCOME ATTRIBUTABLE TO SHAREOWNERS OF THE COCA-COLA COMPANY | C11: 2018 | D11: {=_xlfn.XLOOKUP(B11 &C11,Table3[Metric] &Table3[Year],Table3[Amount],,0)} -> 6434
A12: Balance Sheet | B12: Total Assets | C12: 2009 | D12: {=_xlfn.XLOOKUP(B12 &C12,Table3[Metric] &Table3[Year],Table3[Amount],,0)} -> 48671
A13: Balance Sheet | B13: Total Assets | C13: 2010 | D13: {=_xlfn.XLOOKUP(B13 &C13,Table3[Metric] &Table3[Year],Table3[Amount],,0)} -> 72921
... A31: Cash Flow Statement | B31: Net increase (decrease) during the year | C31: 2018 | D31: {=_xlfn.XLOOKUP(B31 &C31,Table3[Metric] &Table3[Year],Table3[Amount],,0)} -> 2945

Sheet Dashboard
A1: COCA-COLA Company Performance DASHBOARD (2009-2018)
